cabot/__init__.py
cabot/cabot.py
cabot/init.py
cabot/modules/__init__.py
cabot/modules/backend/__init__.py
cabot/modules/backend/Discoball/DIscoball.py.4815329e24180e80d4a3fbc97bb1b178.py
cabot/modules/backend/Discoball/Discoball.py
cabot/modules/backend/Discoball/__init__.py
cabot/modules/backend/TwitchApi/TwitchApi.py
cabot/modules/backend/TwitchApi/__init__.py
cabot/modules/command/__init__.py
cabot/modules/command/TwitchIrc/TwitchIrc.py
cabot/modules/command/TwitchIrc/__init__.py
cabot-core/__init__.py
cabot-core/cabot.py
cabot-core/init.py
cabot_core-0.1.1.dist-info/LICENSE
cabot_core-0.1.1.dist-info/METADATA
cabot_core-0.1.1.dist-info/WHEEL
cabot_core-0.1.1.dist-info/top_level.txt
cabot_core-0.1.1.dist-info/RECORD
