Metadata-Version: 2.1
Name: cabot-core
Version: 0.1.1
Summary: A modular chat bot.
Home-page: https://github.com/centennialarts/cabot
Author: Joseph Hanna
Author-email: josephhanna@centennialarts.com
License: MIT
Download-URL: https://github.com/centennialarts/cabot/archive/master.zip
Keywords: Chatbot,IRC,API
Platform: UNKNOWN
Classifier: Development Status :: 2 - Pre-Alpha
Classifier: Intended Audience :: Developers
Classifier: Topic :: Communications :: Chat :: Internet Relay Chat
Classifier: License :: OSI Approved :: MIT License
Classifier: Programming Language :: Python :: 3
Requires-Dist: irc
Requires-Dist: requests
